[{"name": "\uac80\uc815\uc0c9", "code": "101", "label": "\u0447\u0435\u0440\u043d\u0438\u0442\u044c (black)"}, {"name": "\uac80\uc815\ud22c\ud1a4", "code": "201", "label": "\u0427\u0435\u0440\u043d\u044b\u0439 \u0442\u043e\u043d (Black Tone)"}, {"name": "\ud770\uc0c9", "code": "102", "label": "\u0431\u0435\u043b\u044b\u0439 (White)"}, {"name": "\ud770\uc0c9\ud22c\ud1a4", "code": "202", "label": "\u0411\u0435\u043b\u044b\u0439 \u0434\u0432\u0443\u0445\u0446\u0432\u0435\u0442\u043d\u044b\u0439 (White Two-Tone)"}, {"name": "\uc9c4\uc8fc\uc0c9", "code": "103", "label": "\u0436\u0435\u043c\u0447\u0443\u0436\u043d\u044b\u0439 \u0441\u0435\u0440\u044b\u0439 (pearl gray)"}, {"name": "\uc9c4\uc8fc\ud22c\ud1a4", "code": "203", "label": "\u0416\u0435\u043c\u0447\u0443\u0436\u043d\u044b\u0439 \u0442\u043e\u043d (Pearl Tone)"}, {"name": "\uac08\ub300\uc0c9", "code": "104", "label": "\u041d\u0430\u0433\u0440\u0430\u0434\u0430 (Reward)"}, {"name": "\uac08\ub300\ud22c\ud1a4", "code": "204", "label": "\u041e\u0442\u0440\u043e\u0441\u0442\u043e\u043a (Reed)"}, {"name": "\uccad\uc0c9", "code": "105", "label": "\u0441\u0438\u043d\u0438\u0439 (blue)"}, {"name": "\ube68\uac04\uc0c9", "code": "106", "label": "\u043a\u0440\u0430\u0441\u043d\u044b\u0439 (Red)"}, {"name": "\uc5f0\uae08\uc0c9", "code": "107", "label": "\u041f\u0435\u043d\u0441\u0438\u044f (Pension)"}, {"name": "\ud558\ub298\uc0c9", "code": "108", "label": "\u0413\u043e\u043b\u0443\u0431\u043e\u0435 \u043d\u0435\u0431\u043e (Sky blue)"}, {"name": "\uc8fc\ud669\uc0c9", "code": "109", "label": "\u0430\u043f\u0435\u043b\u044c\u0441\u0438\u043d (Orange)"}, {"name": "\uc950\uc0c9", "code": "110", "label": "\u0441\u0435\u0440\u044b\u0439 (Gray)"}, {"name": "\uac08\uc0c9", "code": "111", "label": "\u043a\u043e\u0440\u0438\u0447\u043d\u0435\u0432\u044b\u0439 (Brown)"}, {"name": "\uac08\uc0c9\ud22c\ud1a4", "code": "211", "label": "\u043a\u043e\u0440\u0438\u0447\u043d\u0435\u0432\u044b\u0439 (Brown)"}, {"name": "\ub2f4\ub179\uc0c9", "code": "112", "label": "\u041f\u043e\u0432\u0440\u0435\u0436\u0434\u0430\u0442\u044c (Damage)"}, {"name": "\uc790\uc8fc\uc0c9", "code": "113", "label": "\u0444\u0438\u043e\u043b\u0435\u0442\u043e\u0432\u044b\u0439 (purple)"}, {"name": "\uc740\uc0c9", "code": "114", "label": "\u0441\u0435\u0440\u0435\u0431\u0440\u043e (silver)"}, {"name": "\uc740\uc0c9\ud22c\ud1a4", "code": "214", "label": "\u0421\u0435\u0440\u0435\u0431\u0440\u044f\u043d\u044b\u0439 \u0442\u043e\u043d (Silver Tone)"}, {"name": "\ub179\uc0c9", "code": "115", "label": "\u0437\u0435\u043b\u0435\u043d\u044b\u0439 (green)"}, {"name": "\ubcf4\ub77c\uc0c9", "code": "116", "label": "\u0444\u0438\u043e\u043b\u0435\u0442\u043e\u0432\u044b\u0439 (purple)"}, {"name": "\uc740\ud68c\uc0c9", "code": "117", "label": "\u0441\u0435\u0440\u044b\u0439 (Gray)"}, {"name": "\uc740\ud558\uc0c9", "code": "118", "label": "\u0422\u043e (The)"}, {"name": "\uae08\uc0c9", "code": "119", "label": "\u0437\u043e\u043b\u043e\u0442\u043e (gold)"}, {"name": "\uae08\uc0c9\ud22c\ud1a4", "code": "219", "label": "\u0417\u043e\u043b\u043e\u0442\u043e\u0439 \u0442\u043e\u043d (Gold-tone)"}, {"name": "\uc5f0\ub450\uc0c9", "code": "120", "label": "\u0441\u0432\u0435\u0442\u043b\u043e-\u0437\u0435\u043b\u0435\u043d\u044b\u0439 (light green)"}, {"name": "\ubd84\ud64d\uc0c9", "code": "121", "label": "\u0440\u043e\u0437\u043e\u0432\u044b\u0439 (pink)"}, {"name": "\uba85\uc740\uc0c9", "code": "122", "label": "\u0418\u043c\u044f (The name is)"}, {"name": "\uccad\uc625\uc0c9", "code": "123", "label": "\u0421\u0438\u043d\u0438\u0439 (Blue)"}, {"name": "\ub178\ub780\uc0c9", "code": "124", "label": "\u0436\u0435\u043b\u0442\u044b\u0439 (yellow)"}, {"name": "\ub178\ub791\ud22c\ud1a4", "code": "224", "label": "\u0416\u0435\u043b\u0442\u044b\u0439 \u0434\u0432\u0430 \u0442\u043e\u043d\u043d\u0430 (Yellow Two-Tone)"}, {"name": "\ud751\uc7a5\ubbf8\uc0c9", "code": "125", "label": "\u0427\u0435\u0440\u043d\u044b\u0439 \u0447\u0435\u0440\u043d\u044b\u0439 (Black black)"}, {"name": "\ubca0\uc774\uc9c0\uc0c9", "code": "126", "label": "\u0411\u0435\u0436\u0435\u0432\u044b\u0439 (Beige)"}, {"name": "\ub2e4\ud06c\uadf8\ub808\uc774", "code": "127", "label": "\u0422\u0435\u043c\u043d\u043e-\u0441\u0435\u0440\u044b\u0439 (Dark Gray)"}, {"name": "\ub2e4\ud06c\ube14\ub8e8", "code": "128", "label": "\u0422\u0435\u043c\u043d\u043e-\u0441\u0438\u043d\u0438\u0439 (Dark Blue)"}, {"name": "\ud30c\ub780\uc0c9", "code": "129", "label": "\u0441\u0438\u043d\u0438\u0439 (blue)"}, {"name": "\ubbfc\ud2b8\uc0c9", "code": "130", "label": "\u0426\u0432\u0435\u0442 \u043c\u044f\u0442\u044b (Mint color)"}]